pybinaryedge/__init__.py
pybinaryedge/api.py
pybinaryedge/cli.py
pybinaryedge-0.4.dist-info/LICENSE
pybinaryedge-0.4.dist-info/METADATA
pybinaryedge-0.4.dist-info/WHEEL
pybinaryedge-0.4.dist-info/entry_points.txt
pybinaryedge-0.4.dist-info/top_level.txt
pybinaryedge-0.4.dist-info/RECORD
