Metadata-Version: 2.1
Name: pybinaryedge
Version: 0.4
Summary: Python 3 Wrapper for the binary edge API https://www.binaryedge.io/
Home-page: https://github.com/Te-k/pybinaryedge
Author: Tek
Author-email: tek@randhome.io
License: MIT
Keywords: osint
Platform: UNKNOWN
Classifier: Programming Language :: Python :: 3
Classifier: License :: OSI Approved :: MIT License
Classifier: Operating System :: OS Independent
Requires-Dist: requests
Requires-Dist: configparser
